pyqtcmd/__init__.py
pyqtcmd/command.py
pyqtcmd/history.py
pyqtcmd/meta.py
pyqtcmd/uicommand.py
pyqtcmd-1.0.5.dist-info/LICENSE
pyqtcmd-1.0.5.dist-info/METADATA
pyqtcmd-1.0.5.dist-info/WHEEL
pyqtcmd-1.0.5.dist-info/top_level.txt
pyqtcmd-1.0.5.dist-info/RECORD
