Metadata-Version: 2.1
Name: pyqtcmd
Version: 1.0.5
Summary: PyQt6/PyQt5-based Command implementation for undo/redo
Home-page: https://github.com/fraca7/pyqtcmd
Author: Jérôme Laheurte
Author-email: jerome@jeromelaheurte.net
License: MIT
Platform: UNKNOWN
Classifier: License :: OSI Approved :: MIT License
Classifier: Programming Language :: Python :: 3
Classifier: Development Status :: 5 - Production/Stable
Classifier: Intended Audience :: Developers
Classifier: Topic :: Software Development :: Libraries
